llama/__init__.py
llama/convert_llama.py
llama/download.py
llama/download_community.sh
llama/generation.py
llama/llama_infer.py
llama/llama_multigpu.py
llama/llama_quant.py
llama/model_parallel.py
llama/model_single.py
llama/tokenizer.py
llama/version.py
llama/hf/__init__.py
llama/hf/configuration_llama.py
llama/hf/modeling_llama.py
llama/hf/tokenization_llama.py
llama/hf/utils.py
pyllama-0.0.9.dist-info/LICENSE
pyllama-0.0.9.dist-info/METADATA
pyllama-0.0.9.dist-info/WHEEL
pyllama-0.0.9.dist-info/top_level.txt
pyllama-0.0.9.dist-info/RECORD
