Metadata-Version: 2.1
Name: pyllama
Version: 0.0.9
Summary: 🦙 LLaMA: Open and Efficient Foundation Language Models in A Single GPU
Home-page: https://github.com/juncongmoo/pyllama
Author: Juncong Moo;Meta AI
Author-email: JuncongMoo@gmail.com
License: UNKNOWN
Keywords: LLaMA
Platform: UNKNOWN
Classifier: Programming Language :: Python :: 3
Classifier: Programming Language :: Python :: 3.6
Classifier: Programming Language :: Python :: 3.7
Classifier: Programming Language :: Python :: 3.8
Classifier: Programming Language :: Python :: 3.9
Classifier: Programming Language :: Python :: 3.10
Classifier: Programming Language :: Python :: 3.11
License-File: LICENSE
Requires-Dist: torch (>=1.12.0)
Requires-Dist: fairscale (>=0.4.13)
Requires-Dist: fire (~=0.5.0)
Requires-Dist: hiq-python (>=1.1.9)
Requires-Dist: sentencepiece (==0.1.97)
Provides-Extra: full
Requires-Dist: transformers (>=4.26.0) ; extra == 'full'
Requires-Dist: gptq (>=0.0.2) ; extra == 'full'
Requires-Dist: sentencepiece (>=0.1.97) ; extra == 'full'
Requires-Dist: torch (>=1.12.0) ; extra == 'full'
Requires-Dist: fairscale (>=0.4.13) ; extra == 'full'
Requires-Dist: fire (~=0.5.0) ; extra == 'full'
Requires-Dist: hiq-python (>=1.1.9) ; extra == 'full'
Requires-Dist: sentencepiece (==0.1.97) ; extra == 'full'
Provides-Extra: quant
Requires-Dist: transformers (>=4.26.0) ; extra == 'quant'
Requires-Dist: gptq (>=0.0.2) ; extra == 'quant'
Requires-Dist: sentencepiece (>=0.1.97) ; extra == 'quant'
